ckb_g2p/__init__.py
ckb_g2p/cli.py
ckb_g2p/converter.py
ckb_g2p/core/__init__.py
ckb_g2p/core/cache.py
ckb_g2p/core/epenthesizer.py
ckb_g2p/core/evaluator.py
ckb_g2p/core/generator.py
ckb_g2p/core/grapheme_parser.py
ckb_g2p/core/palatalizer.py
ckb_g2p/core/preprocessor.py
ckb_g2p/core/syllabifier.py
ckb_g2p/utils/__init__.py
ckb_g2p/utils/config.py
ckb_g2p-3.0.0.dist-info/METADATA
ckb_g2p-3.0.0.dist-info/WHEEL
ckb_g2p-3.0.0.dist-info/entry_points.txt
ckb_g2p-3.0.0.dist-info/licenses/LICENSE
ckb_g2p-3.0.0.dist-info/RECORD
