Metadata-Version: 2.4
Name: ckb-g2p
Version: 3.0.0
Summary: A linguistically accurate Grapheme-to-Phoneme (G2P) converter and Syllabifier for Central Kurdish (Sorani). Optimized for TTS.
Project-URL: Homepage, https://github.com/RazwanSiktany/ckb_g2p
Project-URL: Repository, https://github.com/RazwanSiktany/ckb_g2p
Project-URL: BugTracker, https://github.com/RazwanSiktany/ckb_g2p/issues
Author: Razwan M. Haji
License-Expression: MIT
License-File: LICENSE
Keywords: g2p,kurdish,linguistics,nlp,phonemizer,sorani,tts
Classifier: Development Status :: 5 - Production/Stable
Classifier: Intended Audience :: Developers
Classifier: Intended Audience :: Science/Research
Classifier: License :: OSI Approved :: MIT License
Classifier: Programming Language :: Python :: 3
Classifier: Topic :: Multimedia :: Sound/Audio :: Speech
Classifier: Topic :: Text Processing :: Linguistic
Requires-Python: >=3.8
Requires-Dist: ckb-textify>=3.0.0
Requires-Dist: pyyaml>=6.0
Provides-Extra: dev
Requires-Dist: pytest>=7.0; extra == 'dev'
Requires-Dist: ruff>=0.3.0; extra == 'dev'
Requires-Dist: streamlit>=1.30.0; extra == 'dev'
